odoo/addons/crm_claim_code/README.rst
odoo/addons/crm_claim_code/__init__.py
odoo/addons/crm_claim_code/__manifest__.py
odoo/addons/crm_claim_code/hooks.py
odoo/addons/crm_claim_code/data/claim_sequence.xml
odoo/addons/crm_claim_code/i18n/bg.po
odoo/addons/crm_claim_code/i18n/crm_claim_code.pot
odoo/addons/crm_claim_code/i18n/de.po
odoo/addons/crm_claim_code/i18n/es.po
odoo/addons/crm_claim_code/i18n/es_MX.po
odoo/addons/crm_claim_code/i18n/es_VE.po
odoo/addons/crm_claim_code/i18n/fr.po
odoo/addons/crm_claim_code/i18n/hr.po
odoo/addons/crm_claim_code/i18n/it.po
odoo/addons/crm_claim_code/i18n/nb.po
odoo/addons/crm_claim_code/i18n/pt_BR.po
odoo/addons/crm_claim_code/i18n/sk.po
odoo/addons/crm_claim_code/i18n/sl.po
odoo/addons/crm_claim_code/i18n/sv.po
odoo/addons/crm_claim_code/models/__init__.py
odoo/addons/crm_claim_code/models/crm_claim.py
odoo/addons/crm_claim_code/readme/CONTRIBUTORS.rst
odoo/addons/crm_claim_code/readme/DESCRIPTION.rst
odoo/addons/crm_claim_code/readme/USAGE.rst
odoo/addons/crm_claim_code/static/description/icon.png
odoo/addons/crm_claim_code/static/description/index.html
odoo/addons/crm_claim_code/tests/__init__.py
odoo/addons/crm_claim_code/tests/test_crm_claim_code.py
odoo/addons/crm_claim_code/views/crm_claim_view.xml
odoo13_addon_crm_claim_code-13.0.1.0.1.dev5.dist-info/METADATA
odoo13_addon_crm_claim_code-13.0.1.0.1.dev5.dist-info/WHEEL
odoo13_addon_crm_claim_code-13.0.1.0.1.dev5.dist-info/top_level.txt
odoo13_addon_crm_claim_code-13.0.1.0.1.dev5.dist-info/RECORD
